{
  "pr_number": 567,
  "title": "migrate projects+sub_projects+tasks into tickets schema (PR3/5)",
  "description": "## Summary\nThird of 5 unified-ticketing PRs. PR1 (#562) created the tickets schema and migrated bug_tickets; PR2 (#565) migrated requirements/features and added pr_events. PR3 lifts the admin project hierarchy.\n\n**Spec:** `docs/superpowers/specs/2026-05-08-unified-ticketing-design.md`\n**Plan:** `docs/superpowers/plans/2026-05-08-unified-ticketing-pr3.md`\n\n### What changes\n- `tickets.tickets` gets a nullable `notes` column (idempotent `ADD COLUMN IF NOT EXISTS` in `initTicketsSchema`).\n- `scripts/migrate-projects-to-tickets.mjs` (new, idempotent, `--apply`-gated, runs as `postgres`):\n  1. Copies `projects` → `tickets.tickets` (type='project', parent_id NULL).\n  2. Copies `sub_projects` → `tickets.tickets` (type='project', parent_id = parent project, brand inherited via JOIN).\n  3. Copies `project_tasks` → `tickets.tickets` (type='task', parent_id = sub_project_id ?? project_id).\n  4. Copies `project_attachments` → `tickets.ticket_attachments`.\n  5. Atomically re-points external FKs (`meetings.project_id`, `time_entries.project_id`, `time_entries.task_id`, `booking_project_links.project_id`) at `tickets.tickets(id)`. UUIDs are preserved end-to-end so existing rows continue to satisfy the new constraints. Aborts loudly if any composite FK is discovered.\n  6. Renames `projects` / `sub_projects` / `project_tasks` / `project_attachments` to `*_legacy` and replaces them with back-compat views over the new schema.\n  7. Defines `tickets._project_status_back()` so the views and the website helpers share the same status-mapping function.\n- `website/src/lib/website-db.ts` — every project helper rewritten to read/write `tickets.tickets` directly. `Project` / `SubProject` / `ProjectTask` / `ProjectAttachment` return shapes are unchanged, so `/admin/projekte` and the Gantt visualization render identically. Status maps `entwurf|geplant→backlog`, `wartend→blocked`, `aktiv→in_progress`, `erledigt→done+shipped`, `archiviert→archived+shipped`.\n- `createProject` now throws if `customer_id` is missing (spec §6 invariant). Migrated rows that already have NULL `customer_id` are tolerated.\n\n### What stays unchanged\n- `/admin/projekte`, `/admin/projekte/[id]`, the Gantt toggle, the Astro/Svelte markup — none of those files are touched.\n- `/admin/kunden/<id>` keeps showing a customer's projects via `listProjects({ customerId })`.\n- `/api/portal/projekte` and `/api/portal/projekttasks/toggle` keep their response shape.\n- CSV export `/api/admin/projekte/export.ts` keeps working — it goes through `listProjects` / `listSubProjects` / `listSubProjectTasks` which are all rewired in place.\n- `pipeline`, `test_results`, `tickets.pr_events`, `bachelorprojekt.v_timeline` — untouched (PR1/PR2 territory).\n\n### Required human follow-up (Deploy Runbook)\nAfter ArgoCD rolls the website pod on both clusters:\n1. `task workspace:backup`\n2. **Per env**, with `task workspace:port-forward ENV=<env>` running:\n   ```\n   PG_PW=$(kubectl --context <env> -n workspace get secret workspace-secrets \\\n     -o jsonpath='{.data.POSTGRES_PASSWORD}' | base64 -d)\n   TRACKING_DB_URL=\"postgres://postgres:${PG_PW}@localhost:5432/website\" \\\n     node scripts/migrate-projects-to-tickets.mjs --apply\n   ```\n   Expected: `{\"projectsMigrated\":N1,\"subProjectsMigrated\":N2,\"tasksMigrated\":N3,\"attachmentsMigrated\":N4,\"fksRePointed\":N5,\"viewsCreated\":4,...,\"mode\":\"apply\"}`. `unknownStatus` must be 0.\n3. Smoke `https://web.<brand>.de/admin/projekte` — projects + Gantt match pre-migration on both brands.\n4. Smoke `https://web.<brand>.de/admin/kunden/<id>` for one customer with projects.\n\nVisibility gap: while pods are rolling and the migration hasn't been applied, `/admin/projekte` shows an empty list. Apply immediately after merge to keep it under ~5 minutes.\n\n### Migration risk-reduction\n- Dry-run is the default; `--apply` is opt-in.\n- All work happens inside one BEGIN/COMMIT — any failure rolls back FK changes and rename together.\n- Old tables are renamed to `*_legacy` (PR5 will drop). Rollback: drop ",
  "category": "feat",
  "scope": "tickets",
  "brand": null,
  "requirement_id": "FA-04",
  "merged_at": "2026-05-08T02:29:55Z",
  "merged_by": "Paddione",
  "bug_refs": []
}
